[
  {
    "channel": "ch5",
    "title": "CH5特集：夜更かしスペシャル",
    "description": "深夜にぴったりのバラエティと特別インタビュー集。",
    "start": "2026-01-04T00:00:00+09:00",
    "end": "2026-01-04T01:00:00+09:00"
  },
  {
   "channel" : "ch5",
    "title": "CH5モーニングショー",
    "description": "ニュース・天気・今日の話題をまとめてお届け。",
    "start": "2026-01-04T04:00:00+09:00",
    "end": "2026-01-04T06:00:00+09:00"
  },
  {
    "channel": "ch5",
    "title": "朝ドラ再放送『翔陽の風』",
    "description": "人気連続ドラマの再放送。家族の絆を描く感動作。",
    "start": "2026-01-04T06:00:00+09:00",
    "end": "2026-01-04T08:00:00+09:00"
  },
  {
    "channel": "ch5",
    "title": "アニメ『未来探偵ナオ』",
    "description": "子供たちに大人気のSFアニメ。未来を変える少年ナオの物語。",
    "start": "2026-01-04T08:00:00+09:00",
    "end": "2026-01-04T09:00:00+09:00"
  },
  {
    "channel": "ch5",
    "title": "CH5のど自慢",
    "description": "視聴者参加型カラオケ番組。今日のチャンピオンは誰だ？",
    "start": "2026-01-04T09:00:00+09:00",
    "end": "2026-01-04T11:00:00+09:00"
  },
  {
    "channel": "ch5",
    "title": "ドキュメンタリー『翔陽の食卓』",
    "description": "地元の食文化を探る旅。今回は心翔け特集。",
    "start": "2026-01-04T11:00:00+09:00",
    "end": "2026-01-04T12:00:00+09:00"
  },
  {
    "channel": "ch5",
    "title": "映画『nko汁の伝説』",
    "description": "翔陽市で生まれた奇跡のレシピを巡る感動の物語。",
    "start": "2026-01-04T12:00:00+09:00",
    "end": "2026-01-04T14:00:00+09:00"
  },
  {
    "channel": "ch5",
    "title": "バラエティ『キタダ劇場』",
    "description": "北田ファミリーが日常を再現。即興ドラマと爆笑トーク。",
    "start": "2026-01-04T14:00:00+09:00",
    "end": "2026-01-04T15:00:00+09:00"
  },
  {
    "channel": "ch5",
    "title": "nkoクラシック名曲集",
    "description": "落ち着いた午後に贈る名曲セレクション。",
    "start": "2026-01-04T15:00:00+09:00",
    "end": "2026-01-04T16:00:00+09:00"
  },
  {
    "channel": "ch5",
    "title": "ニュース翔陽",
    "description": "翔陽市の最新ニュースを速報でお届け。",
    "start": "2026-01-04T16:00:00+09:00",
    "end": "2026-01-04T17:00:00+09:00"
  },
  {
    "channel": "ch5",
    "title": "アニメ『北田蒼真物語』",
    "description": "幼児向け教育アニメ。蒼真の成長を描く感動作。",
    "start": "2026-01-04T17:00:00+09:00",
    "end": "2026-01-04T18:00:00+09:00"
  },
  {
    "channel": "ch5",
    "title": "CH5イブニング",
    "description": "トーク・ニュース・天気予報。夕方の情報番組。",
    "start": "2026-01-04T18:00:00+09:00",
    "end": "2026-01-04T19:00:00+09:00"
  },
  {
    "channel": "ch5",
    "title": "ドラマ『心翔けに咲く』",
    "description": "翔陽の街を舞台にした恋愛ヒューマンドラマ。",
    "start": "2026-01-04T19:00:00+09:00",
    "end": "2026-01-04T21:00:00+09:00"
  },
  {
    "channel": "ch5",
    "title": "討論番組『nkoの目』",
    "description": "政治・社会問題を深掘り。市民の声を届ける。",
    "start": "2026-01-04T21:00:00+09:00",
    "end": "2026-01-04T22:00:00+09:00"
  },
  {
    "channel": "ch5",
    "title": "ドキュメント翔陽『地下の闘技場』",
    "description": "新大津地下闘技場の裏側に迫る。",
    "start": "2026-01-04T22:00:00+09:00",
    "end": "2026-01-04T23:00:00+09:00"
  },
  {
    "channel": "ch5",
    "title": "CH5ナイトショー",
    "description": "音楽とトークで1日を締めくくるバラエティ番組。",
    "start": "2026-01-04T23:00:00+09:00",
    "end": "2026-01-04T24:00:00+09:00"
  }
]